fontit/__init__.py
fontit/fonts/times.ttf
fontit/fonts/timesbd.ttf
fontit/fonts/timesbi.ttf
fontit/fonts/timesi.ttf
fontit/platform.py
fontit/times.py
fontit-0.2.2.dist-info/LICENSE
fontit-0.2.2.dist-info/METADATA
fontit-0.2.2.dist-info/WHEEL
fontit-0.2.2.dist-info/RECORD
