Metadata-Version: 2.1
Name: fontit
Version: 0.2.2
Summary: 
Author: zhangningboo
Author-email: zhangningbo21@mails.ucas.ac.cn
Requires-Python: >=3.8,<4.0
Classifier: Programming Language :: Python :: 3
Classifier: Programming Language :: Python :: 3.8
Classifier: Programming Language :: Python :: 3.9
Classifier: Programming Language :: Python :: 3.10
Classifier: Programming Language :: Python :: 3.11
